setup.cfg
setup.py
sshagentmux/__init__.py
sshagentmux/authorization_proxy.py
sshagentmux/base_agent_request.py
sshagentmux/ssh_agent_mux.py
sshagentmux/upstream_socket_thread.py
sshagentmux/util.py
sshagentmux.egg-info/PKG-INFO
sshagentmux.egg-info/SOURCES.txt
sshagentmux.egg-info/dependency_links.txt
sshagentmux.egg-info/entry_points.txt
sshagentmux.egg-info/not-zip-safe
sshagentmux.egg-info/pbr.json
sshagentmux.egg-info/top_level.txt