Metadata-Version: 1.1
Name: sshagentmux
Version: 0.0.1
Summary: SSH Agent Authorization Proxy and Multiplexer
Home-page: https://github.com/blueboxgroup/sshagentmux
Author: Dustin Lundquist
Author-email: dustin@null-ptr.net
License: Apache2
Download-URL: https://github.com/blueboxgroup/sshagentmux/tarball/v0.0.1
Platform: UNKNOWN
Classifier: Environment :: Console
Classifier: Environment :: Web Environment
Classifier: Intended Audience :: Developers
Classifier: Intended Audience :: System Administrators
Classifier: License :: OSI Approved :: Apache Software License
Classifier: Operating System :: OS Independent
Classifier: Topic :: Software Development :: Libraries :: Python Modules
Classifier: Programming Language :: Python :: 3
Classifier: Programming Language :: Python :: 3.4
Classifier: Programming Language :: Python :: 3.3
Classifier: Programming Language :: Python :: 2.7
Classifier: Programming Language :: Python :: 2.6
